{
  "_fv": 73,
  "_type": "overlay",
  "definition": {
    "priority": "HIGHEST",
    "components": [
      {
        "type": "sprite",
        "data": {
          "sprite": "coin.png",
          "spritesCount": 1,
          "spriteIndex": {
            "fixedValue": 0.0
          },
          "anchorPoint": "TOP_LEFT",
          "x": -2,
          "y": -1,
          "locked": false
        }
      },
      {
        "type": "label",
        "data": {
          "name": "label_proc_coin_calculation",
          "text": {
            "fixedValue": "",
            "name": "CoinCalculation"
          },
          "color": {
            "value": -205,
            "falpha": 0.0
          },
          "anchorPoint": "TOP_LEFT",
          "x": 30,
          "y": 12,
          "locked": false
        }
      },
      {
        "type": "sprite",
        "data": {
          "sprite": "purple_coin.png",
          "spritesCount": 1,
          "spriteIndex": {
            "fixedValue": 0.0
          },
          "anchorPoint": "TOP_LEFT",
          "x": -2,
          "y": 25,
          "locked": false
        }
      },
      {
        "type": "label",
        "data": {
          "name": "label_proc_purple_coin_calculation",
          "text": {
            "fixedValue": "",
            "name": "PurpleCoinCalculation"
          },
          "color": {
            "value": -6749953,
            "falpha": 0.0
          },
          "anchorPoint": "TOP_LEFT",
          "x": 30,
          "y": 37,
          "locked": false
        }
      }
    ],
    "baseTexture": "",
    "overlayTarget": "Ingame",
    "gridSettings": {
      "sx": 18,
      "sy": 18,
      "ox": 11,
      "oy": 15,
      "snapOnGrid": false
    }
  }
}